mcafeesecure_api/__init__.py
mcafeesecure_api/mcafeesecure_api.py
mcafeesecure_api-0.0.5.dist-info/LICENSE
mcafeesecure_api-0.0.5.dist-info/METADATA
mcafeesecure_api-0.0.5.dist-info/WHEEL
mcafeesecure_api-0.0.5.dist-info/top_level.txt
mcafeesecure_api-0.0.5.dist-info/RECORD
