Metadata-Version: 2.1
Name: mcafeesecure-api
Version: 0.0.5
Summary: Interface Package for the McAfee SECURE API
Home-page: https://github.com/zacharyts/
Author: Zachary Collins
Author-email: zachary@mcafeesecure.com
License: UNKNOWN
Platform: UNKNOWN
Classifier: Programming Language :: Python :: 3
Classifier: License :: OSI Approved :: MIT License
Classifier: Operating System :: OS Independent
Requires-Dist: requests
